<?xml version="1.0" encoding="utf-8"?>
<odoo>
        <report 
            id="dde_auto"
            string="Demande autorisation absence"
            model="hr_demandeautoabsence"
            report_type="qweb-pdf"
            file="Gestion_Conges.dde_auto" 
            name="Gestion_Conges.dde_auto"
            groups = "base.group_user"
            menu = "True"/>

<template id="dde_auto">
    <t t-call="web.html_container">
        <t t-foreach="docs" t-as="o">
            <t t-call="web.external_layout">
		            <h6><p style="text-align:right; widht:100%"><span t-field="o.x_localite_id.name"/>, le <span t-field="o.date_oper"/></p></h6>
					<br/>
					<br/>
					<p style="text-align:center; widht:100%"><strong><span t-field="o.x_a"/></strong></p>
					<br/>
					<br/>
					<p style="text-align:right; widht:100%"><strong><span t-field="o.x_destinateur"/></strong></p>
					<br/>
		            <br/>
		            <p style="text-align:left; widht:100%"><strong>Objet : <span t-field="o.x_objet"/></strong></p>
		           	<br/>
		            <br/>
					<p style="text-align:center; widht:100%"><strong><span t-field="o.p_0"/></strong></p>
					<br/>
					<p style="text-align:left; widht:100%"><strong><span t-field="o.p_1"/> <span t-field="o.p_2"/> </strong></p> 
					<br/>
					<p style="text-align:left; widht:100%"><strong><span t-field="o.p_3"/> <span t-field="o.p_4"/> <span t-field="o.p_5"/> </strong></p> 
					<br/>
					<br/>
					<br/>
					<p style="text-align:right; widht:100%"><strong><span t-field="o.p_6"/></strong></p> 
					
             </t>
             </t>
    </t>
</template>
</odoo>